{"geocoded_waypoints": [{"geocoder_status": "OK", "place_id": "ChIJ5RN3Ls3LD4gR0ohr4YdT3Ww", "types": ["premise"]}, {"geocoder_status": "OK", "place_id": "ChIJYQulElExDogRKZmCBkE8dx4", "types": ["locality", "political"]}], "routes": [{"bounds": {"northeast": {"lat": 41.9708051, "lng": -87.6281666}, "southwest": {"lat": 41.7200134, "lng": -87.8153335}}, "copyrights": "Map data \u00a92019", "legs": [{"arrival_time": {"text": "10:50pm", "time_zone": "America/Chicago", "value": 1571543459}, "departure_time": {"text": "8:56pm", "time_zone": "America/Chicago", "value": 1571536598}, "distance": {"text": "29.3 mi", "value": 47121}, "duration": {"text": "1 hour 54 mins", "value": 6861}, "end_address": "Oak Lawn, IL 60453, USA", "end_location": {"lat": 41.7200134, "lng": -87.7479542}, "start_address": "4740 N Olcott Ave, Harwood Heights, IL 60706, USA", "start_location": {"lat": 41.9665585, "lng": -87.8153335}, "steps": [{"distance": {"text": "381 ft", "value": 116}, "duration": {"text": "1 min", "value": 85}, "end_location": {"lat": 41.9669951, "lng": -87.8145131}, "html_instructions": "Walk to Lawrence & Olcott", "polyline": {"points": "_rc_Gxl~vO?s@?EAgBuAA"}, "start_location": {"lat": 41.9665585, "lng": -87.8153335}, "steps": [{"distance": {"text": "223 ft", "value": 68}, "duration": {"text": "1 min", "value": 50}, "end_location": {"lat": 41.9665665, "lng": -87.814517}, "html_instructions": "Head <b>east</b> toward <b>N Olcott Ave</b>", "polyline": {"points": "_rc_Gxl~vO?s@?EAgB"}, "start_location": {"lat": 41.9665585, "lng": -87.8153335}, "travel_mode": "WALKING"}, {"distance": {"text": "157 ft", "value": 48}, "duration": {"text": "1 min", "value": 35}, "end_location": {"lat": 41.9669951, "lng": -87.8145131}, "html_instructions": "Turn <b>left</b> onto <b>N Olcott Ave</b>", "maneuver": "turn-left", "polyline": {"points": "arc_Gvg~vOuAA"}, "start_location": {"lat": 41.9665665, "lng": -87.814517}, "travel_mode": "WALKING"}], "travel_mode": "WALKING"}, {"distance": {"text": "3.1 mi", "value": 4920}, "duration": {"text": "11 mins", "value": 683}, "end_location": {"lat": 41.969826, "lng": -87.76113099999999}, "html_instructions": "Bus towards Jefferson Park Blue Line", "polyline": {"points": "wtc_Grg~vOQ@Ai@Au@?WAcAAm@?[A}AAu@Aq@?_@A_@Ao@?m@?[?UAY?e@Ak@?M?]Ag@?YAw@?_@?E@A?[Cg@Ck@?k@?s@Cw@Cw@Aw@?s@Ci@K_@WQ[EY?c@CU?GC_@H?cA?W?SA}@?QAeB?{B?EA}DAk@?uB?}A?OA{E?UA}E?SAuF@uE?[AoFAg@Jk@AyC?m@?kEEoF?Q?mA?s@A{AAsC?_B?[AuEAmFEm@?QEwD?CCkF?EAmFEqF?U?{ECqF?GCkF?y@AcD?_@lAwA^c@Z_@`@e@?_@?kA@iBCaG?UEmK?aA?YA{@?gBCqG?U?[E{I?QCwB?aA?}@AoA?g@?_BAo@?aBHyFPsFBy@H}CE_@M[g@qAqAdABKBDGDIFQLWVUVSNWPUPMJSNSNK]Ii@CYCGGOKWQ_@QKS@IJDH"}, "start_location": {"lat": 41.966995, "lng": -87.814499}, "transit_details": {"arrival_stop": {"location": {"lat": 41.969826, "lng": -87.76113099999999}, "name": "Jefferson Park Transit Center South Drop Off"}, "arrival_time": {"text": "9:09pm", "time_zone": "America/Chicago", "value": 1571537385}, "departure_stop": {"location": {"lat": 41.966995, "lng": -87.814499}, "name": "Lawrence & Olcott"}, "departure_time": {"text": "8:58pm", "time_zone": "America/Chicago", "value": 1571536702}, "headsign": "Jefferson Park Blue Line", "line": {"agencies": [{"name": "Chicago Transit Authority", "phone": "1 888-YOURCTA", "url": "http://www.transitchicago.com/"}], "color": "#565a5c", "name": "West Lawrence", "short_name": "81W", "text_color": "#ffffff", "url": "http://www.transitchicago.com/bus/81W/", "vehicle": {"icon": "//maps.gstatic.com/mapfiles/transit/iw2/6/bus2.png", "name": "Bus", "type": "BUS"}}, "num_stops": 23}, "travel_mode": "TRANSIT"}, {"distance": {"text": "39 ft", "value": 12}, "duration": {"text": "1 min", "value": 8}, "end_location": {"lat": 41.9697762, "lng": -87.760965}, "html_instructions": "Walk to Jefferson Park", "polyline": {"points": "ufd_GlysvOPM"}, "start_location": {"lat": 41.9698662, "lng": -87.7610294}, "steps": [{"distance": {"text": "39 ft", "value": 12}, "duration": {"text": "1 min", "value": 8}, "end_location": {"lat": 41.9697762, "lng": -87.760965}, "html_instructions": "Head <b>southeast</b>", "polyline": {"points": "ufd_GlysvOPM"}, "start_location": {"lat": 41.9698662, "lng": -87.7610294}, "travel_mode": "WALKING"}], "travel_mode": "WALKING"}, {"distance": {"text": "10.2 mi", "value": 16345}, "duration": {"text": "30 mins", "value": 1770}, "end_location": {"lat": 41.8756654, "lng": -87.63123689999999}, "html_instructions": "Subway towards Forest Park", "polyline": {"points": "kld_GnzsvOEC^mAj@aBTq@pAqCfBqDfA_CTe@DKlCwFn@uAh@kAVg@`AqBTe@|B{Ez@cBrA}BZg@hAkBn@eA^q@d@{@Vc@h@gA@Ch@mA`@kA`@uAb@}ABINs@RgATgADOZyALk@No@Lg@Po@`@oAPg@z@sBVi@Zk@dAaBXa@HOBA^c@^a@d@s@j@s@f@m@v@iAv@yAz@_Bx@}AjK{TpCcGtCeHfE{IdGkMfCuFBC`BjBhCuFBGrA{CVi@Vk@fAyBvEuJdCmFj@oAh@mAv@iBFKRe@Te@Tg@Te@Te@Te@j@mARe@Te@j@mAl@kANYDITe@^u@l@qAXk@Rg@VKbBu@XMh@WxCwAxA}@t@c@t@q@VUpA}Ap@cABITe@Zs@Vc@`BoC^q@l@m@rBsB\\]fBWdC_@F?@?lCCnCCnCCzFGzFGbIIhBAdBkAvFqKvDgHl@kAtB}DV[dBgC`B}BjAuAbAoA`AqA\\k@DEj@_A`@q@|@cBFKTc@h@cAZq@`@w@JQl@kATc@l@kAZo@Te@Vc@^u@`@w@N[r@sAzBiEDK`CuE\\o@FOf@_A\\s@\\q@vAqCvAqC`AkB@ATc@j@iAhAyBbAoBbAqBj@eAVi@bAoBl@kAl@iAbAoBj@iAVe@Te@\\o@l@iAJS`@u@n@gAHQz@{AVc@n@iAdAkBdD_Gb@w@b@y@dAiBbAiBjBeDd@y@Ve@n@gApCaFBEdAmBfAmBXg@FIX[JODIx@{ACC\\k@bFwIjGaLjIeOj@oAn@cB`BcFp@qCbC_FlAaCjAsBxAgCfCuEjAwB|BcExBaE|AoC`CmEjCyE|BaEnCyExBwDfAuBl@gA`CqEvB}DzBwD~DiH`CkEhBgD`CgEfBaDjCsExAaCrAyB~CyEdBmCdBiCpBwCp@eAf@w@rAoBHMFQB_@Dq@AaGAaL?mLAuEA_D?eC?aB?gC?Q?e@?U@K@G@IDMHMJGJAH?PAfIApBAlECX?bCCrBCJ?pBC|BCzAA|@ChBAB?bGIF?bAAf@A~@AV@VJNXDXBZDrHQ@"}, "start_location": {"lat": 41.9707754, "lng": -87.76120379999999}, "transit_details": {"arrival_stop": {"location": {"lat": 41.8756654, "lng": -87.63123689999999}, "name": "LaSalle"}, "arrival_time": {"text": "9:45pm", "time_zone": "America/Chicago", "value": 1571539500}, "departure_stop": {"location": {"lat": 41.9707754, "lng": -87.76120379999999}, "name": "Jefferson Park"}, "departure_time": {"text": "9:15pm", "time_zone": "America/Chicago", "value": 1571537730}, "headsign": "Forest Park", "line": {"agencies": [{"name": "Chicago Transit Authority", "phone": "1 888-YOURCTA", "url": "http://www.transitchicago.com/"}], "color": "#02a7e9", "name": "Blue Line", "text_color": "#ffffff", "url": "http://www.transitchicago.com/blueline/", "vehicle": {"icon": "//maps.gstatic.com/mapfiles/transit/iw2/6/us-chicago-subway.png", "name": "Subway", "type": "SUBWAY"}}, "num_stops": 16}, "travel_mode": "TRANSIT"}, {"distance": {"text": "374 ft", "value": 114}, "duration": {"text": "1 min", "value": 84}, "end_location": {"lat": 41.8754808, "lng": -87.6326203}, "html_instructions": "Walk to LaSalle Street", "polyline": {"points": "yxq~FfnzuO?dB@lD"}, "start_location": {"lat": 41.8754942, "lng": -87.63123809999999}, "steps": [{"distance": {"text": "374 ft", "value": 114}, "duration": {"text": "1 min", "value": 84}, "end_location": {"lat": 41.8754808, "lng": -87.6326203}, "html_instructions": "Head <b>west</b> on <b>W Congress Pkwy</b>/<wbr/><b>W Ida B. Wells Dr</b> toward <b>S LaSalle St</b>", "polyline": {"points": "yxq~FfnzuO?dB@lD"}, "start_location": {"lat": 41.8754942, "lng": -87.63123809999999}, "travel_mode": "WALKING"}], "travel_mode": "WALKING"}, {"distance": {"text": "11.7 mi", "value": 18851}, "duration": {"text": "22 mins", "value": 1320}, "end_location": {"lat": 41.7214484, "lng": -87.66730659999999}, "html_instructions": "Train towards Joliet", "polyline": {"points": "swq~F|szuOZGdBC\\?\\?|AAjBAjBAD?v@@b@?H?X@X@\\@h@ApDEt@?`@Ar@?n@EnAOrD_@NA`CYl@I`@GBA\\Kb@M|EaBf@Qf@Qb@KVEZEh@Ej@AJ?bIId@?`@BnCHl@BjBFj@DH@F@PBp@LH@L@JB?FNBL?^@jBCR?jBCjAA^?fAAR?RAt@?\\?DAT?L?PAP?P?PAb@CN?RApAGXAJAZA^Ab@?t@At@Ar@?RAH?XADA\\CNA`@G^GBAXE~@Uf@MZID?LETCLAjBWVEH?xBM\\A^ArDE@?`@?tA@x@?jBCnBAV?@?`AAj@AnBAV?t@C|AEt@AP?b@AF?|DELAL?tJGnCCvEEb@AjBAb@Ab@?fAAfAAh@Al@AF?b@?nAAb@Ab@?fAAvEEb@Ab@?b@Ab@?b@Ab@?b@?b@AfAAb@?fAApACX?b@?fAAp@AT?b@AH?|@Az@A?Tx@AbVQ`X[nBCnDAfHKhF@|ZYle@e@|d@]jYWrVObUWla@Y~RWdIAzCLL@bBR`Cv@vCfAhFtBfFjBdD`AtCx@rDr@zK|CvXvHzQ|EpIbCxMrDtSbFtPdFjD|@hJzBzBl@|A\\zJnCjMfDlNzDdN~DlRdFfBh@@G^JF@XH`@LPD`@JB@\\Jn@THDVJ`@N~@XTHJB`@LdAZj@LHB`@Lt@Zd@NXFNFp@^b@\\f@h@^j@N\\P`@HVHRT`ALz@Fr@@Z?b@?JCpAC|@C\\?PAJAb@ADAh@?`@?L?r@?l@?b@?JBnC?l@?p@B~E?z@BlE@zE@XBnDAf@DnF@zDD|H@dHDnBFx@@N@LJ~@XdB\\pAPt@Rh@f@hA`@p@f@r@r@|@t@t@f@^h@\\n@`@lAd@\\Hj@NxAP^Dh@?p@@T@|CFtGPtOXdHNJ??a@"}, "start_location": {"lat": 41.87529989999999, "lng": -87.63214769999999}, "transit_details": {"arrival_stop": {"location": {"lat": 41.7214484, "lng": -87.66730659999999}, "name": "95th Street Station"}, "arrival_time": {"text": "10:22pm", "time_zone": "America/Chicago", "value": 1571541720}, "departure_stop": {"location": {"lat": 41.87529989999999, "lng": -87.63214769999999}, "name": "LaSalle Street"}, "departure_time": {"text": "10:00pm", "time_zone": "America/Chicago", "value": 1571540400}, "headsign": "Joliet", "line": {"agencies": [{"name": "Metra Metropolitan Rail", "url": "https://metrarail.com/"}], "color": "#e02400", "name": "Rock Island", "short_name": "RI", "text_color": "#ffffff", "url": "https://metrarail.com/maps-schedules/train-lines/RI", "vehicle": {"icon": "//maps.gstatic.com/mapfiles/transit/iw2/6/rail2.png", "name": "Train", "type": "HEAVY_RAIL"}}, "num_stops": 5}, "travel_mode": "TRANSIT"}, {"distance": {"text": "13 ft", "value": 4}, "duration": {"text": "1 min", "value": 3}, "end_location": {"lat": 41.72126189999999, "lng": -87.6665635}, "html_instructions": "Walk to 95th Street & Vanderpoel", "polyline": {"points": "aus}FbkavO?ADA"}, "start_location": {"lat": 41.7212947, "lng": -87.6665769}, "steps": [{"distance": {"text": "13 ft", "value": 4}, "duration": {"text": "1 min", "value": 3}, "end_location": {"lat": 41.72126189999999, "lng": -87.6665635}, "html_instructions": "Head <b>south</b> toward <b>W 95th St</b><div style=\"font-size:0.9em\">Destination will be on the left</div>", "polyline": {"points": "aus}FbkavO?ADA"}, "start_location": {"lat": 41.7212947, "lng": -87.6665769}, "travel_mode": "WALKING"}], "travel_mode": "WALKING"}, {"distance": {"text": "4.2 mi", "value": 6679}, "duration": {"text": "17 mins", "value": 1020}, "end_location": {"lat": 41.7200719, "lng": -87.7469898}, "html_instructions": "Bus towards 9900 Industrial Ave", "polyline": {"points": "{ts}FxjavOBrC@|JHpQDxKBnPHhNFhS?rIFjWFnSDdOHxV@vKDnMDrI@nNFnLJdP?nND|MFbNH~RDfJH|LLlPFxOH`JHdOFlNLlQHpRJpO"}, "start_location": {"lat": 41.7212643, "lng": -87.66653079999999}, "transit_details": {"arrival_stop": {"location": {"lat": 41.7200719, "lng": -87.7469898}, "name": "95th St & Museum Dr"}, "arrival_time": {"text": "10:50pm", "time_zone": "America/Chicago", "value": 1571543400}, "departure_stop": {"location": {"lat": 41.7212643, "lng": -87.66653079999999}, "name": "95th Street & Vanderpoel"}, "departure_time": {"text": "10:33pm", "time_zone": "America/Chicago", "value": 1571542380}, "headsign": "9900 Industrial Ave", "line": {"agencies": [{"name": "Pace Suburban Bus", "phone": "1 847-364-PACE", "url": "http://www.pacebus.com/"}], "color": "#00539f", "name": "95th Street", "short_name": "381", "text_color": "#ffffff", "vehicle": {"icon": "//maps.gstatic.com/mapfiles/transit/iw2/6/bus2.png", "name": "Bus", "type": "BUS"}}, "num_stops": 32}, "travel_mode": "TRANSIT"}, {"distance": {"text": "262 ft", "value": 80}, "duration": {"text": "1 min", "value": 58}, "end_location": {"lat": 41.7200134, "lng": -87.7479542}, "html_instructions": "Walk to Oak Lawn, IL 60453, USA", "polyline": {"points": "cms}FtaqvOApA@X@rA"}, "start_location": {"lat": 41.7200227, "lng": -87.7469904}, "steps": [{"distance": {"text": "262 ft", "value": 80}, "duration": {"text": "1 min", "value": 58}, "end_location": {"lat": 41.7200134, "lng": -87.7479542}, "html_instructions": "Head <b>west</b> on <b>W 95th St</b> toward <b>S 51st Ave</b>", "polyline": {"points": "cms}FtaqvOApA@X@rA"}, "start_location": {"lat": 41.7200227, "lng": -87.7469904}, "travel_mode": "WALKING"}], "travel_mode": "WALKING"}], "traffic_speed_entry": [], "via_waypoint": []}], "overview_polyline": {"points": "_rc_Gxl~vO?y@AgBuAAQ?C_BCeDEeFG{GAmBAwA@GCcACwAI{EC}AK_@WQ[EY?y@CGC_@H?{ACiECkJA_MEg_@Jk@AyC?yFEcKCkJCcME_AImLGqUG_PAcElB{B|@eA?kBGoWK_\\GqO?aBHyFTmHH}CE_@u@mBqAdABKBDGD[Tm@n@oA~@g@^UgAGa@Sg@Q_@QKS@IJDHGSPMgEn@ECjAoDTq@pAqCnDqHxE_KxCkGxD_InBeD~D_H`AkBj@qAbAaDf@gB~@sEfA}Er@_ClA{Cr@uA~AcClAwApD_FrByDx@}AjK{TpCcGtCeHlMgXjCyF`BjBhCuFvAcDn@uA~GoNpD}H|BiFvAyCjB_EnB}D|ByERg@VK|BcAbEoBnCaBlAgApA}Ap@cAXo@r@wA`CaE`DaD\\]fBWlC_@nLKd\\[dBkAvFqKdFsJtB}DV[fEeGnCeD~A}Bp@eA~AuCbBeDhF_KfWag@`V_e@rYeh@jG}K`BuC`@e@PYx@{ACC`GcKvQg\\j@oAn@cB`BcFp@qCpEaJdD{FjMsU~E}IhG{KhGqKtB}DxFoKzBwD~DiHjFsJhFiJdFuIrFsInJuNzBgDP_@HqACcTCi\\?aH@a@BQN[JGJAZAxLC~MKvIIbRUV@VJNXDXBZDrHQ@b@?@rGb@}AZGbCCzBAtGA`BBfA?fFEdCGtKkAnAQ`@MpIsCz@QdAK`LKjIXnALtAT?FNBl@@vHI~FE|CIrCMnDEjBCtAOtEcAfDc@`EQtDEvB@lHE~EE`FK|WUzb@_@jTQtBCxBC?Tx@AbVQ`X[~GEfHKhF@jaA_Ah_Au@rVObUWla@Y~RWdIAzCLpBT`Cv@vCfAhFtBfFjBzHzBrDr@zK|CvXvHzQ|EpIbCxMrDtSbFtPdFtOxDzBl@|A\\fYvHr]zJtUnG@G^J`@Jr@Rd@LlA`@bCz@hCv@t@PvAh@nA^p@^b@\\fAtAt@jBT`ALz@HnA?n@GnCG~AC~A?pCNn]HbSFbRDnBFx@B\\d@dDn@fCz@rBhAdBhBrBpA|@n@`@lAd@hAXxBVnGJjXj@pHN?a@^qCDC?EBrCJn]Hh]Prb@F~a@Ltc@Jpc@JbXH~[JdP?nNL`]Nf^h@fz@Pr^V~d@JpOH?ApABlB"}, "summary": "", "warnings": ["Walking directions are in beta. Use caution \u2013 This route may be missing sidewalks or pedestrian paths."], "waypoint_order": []}], "status": "OK"}